dynamic_ansible_inventory/ansible_inventory.py
dynamic_ansible_inventory/test_ansible_inventory.py
dynamic_ansible_inventory-0.2.dist-info/DESCRIPTION.rst
dynamic_ansible_inventory-0.2.dist-info/METADATA
dynamic_ansible_inventory-0.2.dist-info/RECORD
dynamic_ansible_inventory-0.2.dist-info/WHEEL
dynamic_ansible_inventory-0.2.dist-info/metadata.json
dynamic_ansible_inventory-0.2.dist-info/top_level.txt
